<?xml version="1.0" encoding="UTF-8"?>
<!DOCTYPE mapper PUBLIC "-//mybatis.org//DTD Mapper 3.0//EN" "http://mybatis.org/dtd/mybatis-3-mapper.dtd">
<mapper namespace="com.fkapi.datebase.dao.vcc_orderMapper">
  <resultMap id="BaseResultMap" type="com.fkapi.datebase.domain.vcc_order">
    <!--
      WARNING - @mbg.generated
      This element is automatically generated by MyBatis Generator, do not modify.
    -->
    <id column="ORDER_NO" jdbcType="VARCHAR" property="orderNo" />
    <result column="MERCHANT_NO" jdbcType="VARCHAR" property="merchantNo" />
    <result column="CARD_NO" jdbcType="VARCHAR" property="cardNo" />
    <result column="SUBMIT_TIME" jdbcType="TIMESTAMP" property="submitTime" />
    <result column="TRANS_AMOUNT" jdbcType="DECIMAL" property="transAmount" />
    <result column="RETURN_AMOUNT" jdbcType="DECIMAL" property="returnAmount" />
    <result column="TRANS_TIME" jdbcType="TIMESTAMP" property="transTime" />
    <result column="REVOKED_TIME" jdbcType="TIMESTAMP" property="revokedTime" />
    <result column="ORDER_STATUS" jdbcType="CHAR" property="orderStatus" />
    <result column="AUDIT_STATUS" jdbcType="CHAR" property="auditStatus" />
    <result column="LIQUIDATION_TIME" jdbcType="TIMESTAMP" property="liquidationTime" />
    <result column="CREATE_TIME" jdbcType="TIMESTAMP" property="createTime" />
    <result column="UPDATE_TIME" jdbcType="TIMESTAMP" property="updateTime" />
    <result column="VERSION" jdbcType="BIGINT" property="version" />
  </resultMap>
  <sql id="Base_Column_List">
    <!--
      WARNING - @mbg.generated
      This element is automatically generated by MyBatis Generator, do not modify.
    -->
    ORDER_NO, MERCHANT_NO, CARD_NO, SUBMIT_TIME, TRANS_AMOUNT, RETURN_AMOUNT, TRANS_TIME, 
    REVOKED_TIME, ORDER_STATUS, AUDIT_STATUS, LIQUIDATION_TIME, CREATE_TIME, UPDATE_TIME, 
    VERSION
  </sql>
  <select id="selectByPrimaryKey" parameterType="java.lang.String" resultMap="BaseResultMap">
    <!--
      WARNING - @mbg.generated
      This element is automatically generated by MyBatis Generator, do not modify.
    -->
    select 
    <include refid="Base_Column_List" />
    from vcc_order
    where ORDER_NO = #{orderNo,jdbcType=VARCHAR}
  </select>
  <delete id="deleteByCarNo" parameterType="java.lang.String">
    <!--
      WARNING - @mbg.generated
      This element is automatically generated by MyBatis Generator, do not modify.
    -->
    delete from vcc_order
    where CARD_NO = #{cardNo,jdbcType=VARCHAR}
  </delete>
  <insert id="insert" parameterType="com.fkapi.datebase.domain.vcc_order">
    <!--
      WARNING - @mbg.generated
      This element is automatically generated by MyBatis Generator, do not modify.
    -->
    insert into vcc_order (ORDER_NO, MERCHANT_NO, CARD_NO, 
      SUBMIT_TIME, TRANS_AMOUNT, RETURN_AMOUNT, 
      TRANS_TIME, REVOKED_TIME, ORDER_STATUS, 
      AUDIT_STATUS, LIQUIDATION_TIME, CREATE_TIME, 
      UPDATE_TIME, VERSION)
    values
    <foreach collection="list" item="item" index="index"
             separator=",">
    (#{item.orderNo}, #{item.merchantNo}, #{item.cardNo}, #{item.submitTime}, '100', #{item.returnAmount}, #{item.transTime},
      NULL, #{item.orderStatus}, NULL, NULL, #{item.createTime}, #{item.updateTime}, '1')
    </foreach>
  </insert>
  <insert id="insertSelective" parameterType="com.fkapi.datebase.domain.vcc_order">
    <!--
      WARNING - @mbg.generated
      This element is automatically generated by MyBatis Generator, do not modify.
    -->
    insert into vcc_order
    <trim prefix="(" suffix=")" suffixOverrides=",">
      <if test="orderNo != null">
        ORDER_NO,
      </if>
      <if test="merchantNo != null">
        MERCHANT_NO,
      </if>
      <if test="cardNo != null">
        CARD_NO,
      </if>
      <if test="submitTime != null">
        SUBMIT_TIME,
      </if>
      <if test="transAmount != null">
        TRANS_AMOUNT,
      </if>
      <if test="returnAmount != null">
        RETURN_AMOUNT,
      </if>
      <if test="transTime != null">
        TRANS_TIME,
      </if>
      <if test="revokedTime != null">
        REVOKED_TIME,
      </if>
      <if test="orderStatus != null">
        ORDER_STATUS,
      </if>
      <if test="auditStatus != null">
        AUDIT_STATUS,
      </if>
      <if test="liquidationTime != null">
        LIQUIDATION_TIME,
      </if>
      <if test="createTime != null">
        CREATE_TIME,
      </if>
      <if test="updateTime != null">
        UPDATE_TIME,
      </if>
      <if test="version != null">
        VERSION,
      </if>
    </trim>
    <trim prefix="values (" suffix=")" suffixOverrides=",">
      <if test="orderNo != null">
        #{orderNo,jdbcType=VARCHAR},
      </if>
      <if test="merchantNo != null">
        #{merchantNo,jdbcType=VARCHAR},
      </if>
      <if test="cardNo != null">
        #{cardNo,jdbcType=VARCHAR},
      </if>
      <if test="submitTime != null">
        #{submitTime,jdbcType=TIMESTAMP},
      </if>
      <if test="transAmount != null">
        #{transAmount,jdbcType=DECIMAL},
      </if>
      <if test="returnAmount != null">
        #{returnAmount,jdbcType=DECIMAL},
      </if>
      <if test="transTime != null">
        #{transTime,jdbcType=TIMESTAMP},
      </if>
      <if test="revokedTime != null">
        #{revokedTime,jdbcType=TIMESTAMP},
      </if>
      <if test="orderStatus != null">
        #{orderStatus,jdbcType=CHAR},
      </if>
      <if test="auditStatus != null">
        #{auditStatus,jdbcType=CHAR},
      </if>
      <if test="liquidationTime != null">
        #{liquidationTime,jdbcType=TIMESTAMP},
      </if>
      <if test="createTime != null">
        #{createTime,jdbcType=TIMESTAMP},
      </if>
      <if test="updateTime != null">
        #{updateTime,jdbcType=TIMESTAMP},
      </if>
      <if test="version != null">
        #{version,jdbcType=BIGINT},
      </if>
    </trim>
  </insert>
  <update id="updateByPrimaryKeySelective" parameterType="com.fkapi.datebase.domain.vcc_order">
    <!--
      WARNING - @mbg.generated
      This element is automatically generated by MyBatis Generator, do not modify.
    -->
    update vcc_order
    <set>
      <if test="merchantNo != null">
        MERCHANT_NO = #{merchantNo,jdbcType=VARCHAR},
      </if>
      <if test="cardNo != null">
        CARD_NO = #{cardNo,jdbcType=VARCHAR},
      </if>
      <if test="submitTime != null">
        SUBMIT_TIME = #{submitTime,jdbcType=TIMESTAMP},
      </if>
      <if test="transAmount != null">
        TRANS_AMOUNT = #{transAmount,jdbcType=DECIMAL},
      </if>
      <if test="returnAmount != null">
        RETURN_AMOUNT = #{returnAmount,jdbcType=DECIMAL},
      </if>
      <if test="transTime != null">
        TRANS_TIME = #{transTime,jdbcType=TIMESTAMP},
      </if>
      <if test="revokedTime != null">
        REVOKED_TIME = #{revokedTime,jdbcType=TIMESTAMP},
      </if>
      <if test="orderStatus != null">
        ORDER_STATUS = #{orderStatus,jdbcType=CHAR},
      </if>
      <if test="auditStatus != null">
        AUDIT_STATUS = #{auditStatus,jdbcType=CHAR},
      </if>
      <if test="liquidationTime != null">
        LIQUIDATION_TIME = #{liquidationTime,jdbcType=TIMESTAMP},
      </if>
      <if test="createTime != null">
        CREATE_TIME = #{createTime,jdbcType=TIMESTAMP},
      </if>
      <if test="updateTime != null">
        UPDATE_TIME = #{updateTime,jdbcType=TIMESTAMP},
      </if>
      <if test="version != null">
        VERSION = #{version,jdbcType=BIGINT},
      </if>
    </set>
    where ORDER_NO = #{orderNo,jdbcType=VARCHAR}
  </update>
  <update id="updateByPrimaryKey" parameterType="com.fkapi.datebase.domain.vcc_order">
    <!--
      WARNING - @mbg.generated
      This element is automatically generated by MyBatis Generator, do not modify.
    -->
    update vcc_order
    set MERCHANT_NO = #{merchantNo,jdbcType=VARCHAR},
      CARD_NO = #{cardNo,jdbcType=VARCHAR},
      SUBMIT_TIME = #{submitTime,jdbcType=TIMESTAMP},
      TRANS_AMOUNT = #{transAmount,jdbcType=DECIMAL},
      RETURN_AMOUNT = #{returnAmount,jdbcType=DECIMAL},
      TRANS_TIME = #{transTime,jdbcType=TIMESTAMP},
      REVOKED_TIME = #{revokedTime,jdbcType=TIMESTAMP},
      ORDER_STATUS = #{orderStatus,jdbcType=CHAR},
      AUDIT_STATUS = #{auditStatus,jdbcType=CHAR},
      LIQUIDATION_TIME = #{liquidationTime,jdbcType=TIMESTAMP},
      CREATE_TIME = #{createTime,jdbcType=TIMESTAMP},
      UPDATE_TIME = #{updateTime,jdbcType=TIMESTAMP},
      VERSION = #{version,jdbcType=BIGINT}
    where ORDER_NO = #{orderNo,jdbcType=VARCHAR}
  </update>
</mapper>